{"is_source_file": true, "format": "Python", "description": "This is a Python source file defining a data class for simplified text representations and a function for rule-based content simplification across different levels.", "external_files": ["src/db/models"], "external_methods": ["LevelEnum"], "published": ["deterministic_simplify", "SimplifiedTexts"], "classes": [{"name": "SimplifiedTexts", "description": "Container for simplified results across levels."}], "methods": [{"name": "str _normalize_text(text: str)", "description": "Trim whitespace and normalize spacing.", "scope": "", "scopeKind": ""}, {"name": "str deterministic_simplify(title: str, content: str, level: LevelEnum)", "description": "Performs deterministic, rule-based content simplification based on specified level.", "scope": "", "scopeKind": ""}], "calls": ["_normalize_text"], "search-terms": ["simplify", "deterministic", "content normalization", "LevelEnum", "simplification levels"], "state": 2, "file_id": 11, "knowledge_revision": 28, "git_revision": "", "ctags": [{"_type": "tag", "name": "SimplifiedTexts", "path": "/home/kavia/workspace/code-generation/simplifylearn-179157-179166/explainlike5_backend/src/services/simplifier.py", "pattern": "/^class SimplifiedTexts:$/", "language": "Python", "kind": "class"}, {"_type": "tag", "name": "_normalize_text", "path": "/home/kavia/workspace/code-generation/simplifylearn-179157-179166/explainlike5_backend/src/services/simplifier.py", "pattern": "/^def _normalize_text(text: str) -> str:$/", "language": "Python", "typeref": "typename:str", "kind": "function", "signature": "(text: str)"}, {"_type": "tag", "name": "deterministic_simplify", "path": "/home/kavia/workspace/code-generation/simplifylearn-179157-179166/explainlike5_backend/src/services/simplifier.py", "pattern": "/^def deterministic_simplify(title: str, content: str, level: LevelEnum) -> str:$/", "language": "Python", "typeref": "typename:str", "kind": "function", "signature": "(title: str, content: str, level: LevelEnum)"}], "hash": "02c475605b929f089503048a1f7e6754", "format-version": 4, "code-base-name": "explainlike5_backend", "filename": "explainlike5_backend/src/services/simplifier.py", "revision_history": [{"28": ""}]}